tests/__init__.py
tests/tests.py
s3_zip_uploader_Ivan_Yukish-0.0.4.dist-info/LICENCE
s3_zip_uploader_Ivan_Yukish-0.0.4.dist-info/METADATA
s3_zip_uploader_Ivan_Yukish-0.0.4.dist-info/WHEEL
s3_zip_uploader_Ivan_Yukish-0.0.4.dist-info/top_level.txt
s3_zip_uploader_Ivan_Yukish-0.0.4.dist-info/RECORD
