Metadata-Version: 2.1
Name: s3-zip-uploader-Ivan-Yukish
Version: 0.0.4
Summary: Upload zip files to s3
Home-page: https://github.com/IvanYukish/s3_zip_uploader
Author: Yukish Ivan
Author-email: <iwan.jukisch@gmail.com>
Keywords: python,zip,upload file,s3
Classifier: Development Status :: 1 - Planning
Classifier: Intended Audience :: Developers
Classifier: Programming Language :: Python :: 3
Classifier: Operating System :: Unix
Classifier: Operating System :: MacOS :: MacOS X
Classifier: Operating System :: Microsoft :: Windows
License-File: LICENCE
Requires-Dist: boto3
Requires-Dist: requests
Requires-Dist: pytest
